CHANGELOG.md
cmd_assist/__init__.py
cmd_assist/ai_assist/__init__.py
cmd_assist/ai_assist/query_handler.py
cmd_assist/backup_factory.py
cmd_assist/backup_handlers/__init__.py
cmd_assist/backup_handlers/aws.py
cmd_assist/backup_handlers/exceptions.py
cmd_assist/backup_handlers/local.py
cmd_assist/backup_service.py
cmd_assist/cli_manager.py
cmd_assist/command_repository.py
cmd_assist/configuration/__init__.py
cmd_assist/configuration/base.py
cmd_assist/configuration/config_handler.py
cmd_assist/configuration/config_manager.py
cmd_assist/configuration/config_util.py
cmd_assist/configuration/models.py
cmd_assist/configuration/resources/config.yaml
cmd_assist/constants.py
cmd_assist/file_utils.py
cmd_assist/logging_config.py
resources/config.yaml
cmd_assist-0.1.11.dist-info/METADATA
cmd_assist-0.1.11.dist-info/WHEEL
cmd_assist-0.1.11.dist-info/entry_points.txt
cmd_assist-0.1.11.dist-info/RECORD
