Metadata-Version: 2.1
Name: cmd_assist
Version: 0.1.11
Summary: A tool to save and retrieve frequently used commands.
License: MIT
Keywords: commands,CLI,tools
Author: Darren Rabbitt
Author-email: dev@darrenrabbitt.com
Maintainer: Darren Rabbitt
Maintainer-email: dev@darrenrabbitt.com
Requires-Python: >=3.9,<4.0
Classifier: License :: OSI Approved :: MIT License
Classifier: Programming Language :: Python :: 3
Classifier: Programming Language :: Python :: 3.9
Classifier: Programming Language :: Python :: 3.10
Classifier: Programming Language :: Python :: 3.11
Classifier: Programming Language :: Python :: 3.12
Requires-Dist: PyYAML (>=6.0.1)
Requires-Dist: aioboto3 (>=13.1.1,<14.0.0)
Requires-Dist: argparse (>=1.4.0,<2.0.0)
Requires-Dist: asyncio (>=3.4.3,<4.0.0)
Requires-Dist: boto3 (>=1.17.49)
Requires-Dist: botocore (>=1.34.70,<1.34.132)
Requires-Dist: click (>=7.1.2)
Requires-Dist: jsonschema (>=4.23.0,<5.0.0)
Requires-Dist: openai (==0.28)
Requires-Dist: pydantic (>=2.8.2,<3.0.0)
Requires-Dist: pydantic-settings (>=2.3.4,<3.0.0)
Requires-Dist: python-dotenv (>=0.17.1)
Requires-Dist: requests (>=2.32.3,<3.0.0)
